PS3838/PS3838.py
PS3838/PS3838Bet.py
PS3838/PS3838Retrieve.py
PS3838/_PS3838Bet.py
PS3838/_PS3838Customer.py
PS3838/_PS3838Retrieve.py
PS3838/__init__.py
PS3838/_telegram/__init__.py
PS3838/_telegram/telegram_bot.py
PS3838/_tests/__init__.py
PS3838/_tests/test_Bet.py
PS3838/_tests/test_Retrieve.py
PS3838/_tests/test_betting.py
PS3838/_tests/test_change_bet.py
PS3838/_tests/test_check_credentials.py
PS3838/_tests/test_check_list_matches.py
PS3838/_tests/test_check_match.py
PS3838/_tests/test_find_best_match.py
PS3838/_tests/test_find_league_id.py
PS3838/_tests/test_find_match.py
PS3838/_tests/test_get_team_odds.py
PS3838/_tests/test_is_already_bet.py
PS3838/_tests/test_normalize_name.py
PS3838/_tests/test_retrieve_match.py
PS3838/_tests/test_retrieve_matches.py
PS3838/_tests/test_retrieving.py
PS3838/_tests/test_verify_result.py
PS3838/_utils/__init__.py
PS3838/_utils/constants.py
PS3838/_utils/errors.py
PS3838/_utils/leagues_correspondency.py
PS3838/_utils/tools_check.py
PS3838/_utils/tools_code.py
PS3838/_utils/tools_code_specific_matches.py
PS3838/telegram/__init__.py
PS3838/telegram/telegram_bot.py
PS3838/tests/__init__.py
PS3838/tests/test_Bet.py
PS3838/tests/test_Retrieve.py
PS3838/tests/test_betting.py
PS3838/tests/test_change_bet.py
PS3838/tests/test_check_credentials.py
PS3838/tests/test_check_list_matches.py
PS3838/tests/test_check_match.py
PS3838/tests/test_find_best_match.py
PS3838/tests/test_find_league_id.py
PS3838/tests/test_find_match.py
PS3838/tests/test_get_team_odds.py
PS3838/tests/test_is_already_bet.py
PS3838/tests/test_normalize_name.py
PS3838/tests/test_retrieve_match.py
PS3838/tests/test_retrieve_matches.py
PS3838/tests/test_retrieving.py
PS3838/tests/test_verify_result.py
PS3838/utils/__init__.py
PS3838/utils/constants.py
PS3838/utils/errors.py
PS3838/utils/leagues_correspondency.py
PS3838/utils/tools_check.py
PS3838/utils/tools_code.py
PS3838-0.4.2.dist-info/LICENSE
PS3838-0.4.2.dist-info/METADATA
PS3838-0.4.2.dist-info/WHEEL
PS3838-0.4.2.dist-info/top_level.txt
PS3838-0.4.2.dist-info/RECORD
