Metadata-Version: 2.1
Name: PS3838
Version: 0.4.2
Summary: A package to interact with the PS3838 API, especially to retrieve odds and bet automatically.
Home-page: https://github.com/gaetanlefournis/PS3838.git
Author: Gaëtan Le Fournis
Author-email: gaetanlf22@gmail.com
License: MIT
Project-URL: Bug Reports, https://github.com/gaetanlefournis/PS3838/issues
Project-URL: Source, https://github.com/gaetanlefournis/PS3838
Keywords: PS3838,bet,betting,odds,football,soccer
Platform: UNKNOWN
Classifier: Development Status :: 4 - Beta
Classifier: License :: OSI Approved :: MIT License
Classifier: Programming Language :: Python
Classifier: Programming Language :: Python :: 3
Classifier: Programming Language :: Python :: 3.7
Classifier: Programming Language :: Python :: 3.8
Classifier: Programming Language :: Python :: 3.9
Classifier: Programming Language :: Python :: 3.10
Classifier: Natural Language :: English
License-File: LICENSE
Requires-Dist: Levenshtein (>=0.25.1)
Requires-Dist: PyYAML (>=6.0.1)
Requires-Dist: anyio (>=4.4.0)
Requires-Dist: httpx (>=0.27.0)
Requires-Dist: python-dotenv (>=1.0.1)
Requires-Dist: rapidfuzz (>=3.9.4)
Requires-Dist: requests (>=2.32.3)
Provides-Extra: dev
Requires-Dist: pytest-cov (>=5.0.0) ; extra == 'dev'
Requires-Dist: pytest (>=8.2.2) ; extra == 'dev'
